rxn_models/__init__.py
rxn_models/rxn_models.py
rxnmodel-0.1.11.dist-info/LICENSE
rxnmodel-0.1.11.dist-info/WHEEL
rxnmodel-0.1.11.dist-info/METADATA
rxnmodel-0.1.11.dist-info/RECORD
