Metadata-Version: 2.1
Name: rxnmodel
Version: 0.1.11
Summary: Reaction models for thermokinetic analysis
License: MIT
Keywords: reaction model,non-isothermal kinetics,isoconversional computations
Author: ErickErock
Author-email: ramirez.orozco.erick@gmail.com
Requires-Python: >=3.7,<4.0
Classifier: License :: OSI Approved :: MIT License
Classifier: Programming Language :: Python :: 3
Classifier: Programming Language :: Python :: 3.10
Classifier: Programming Language :: Python :: 3.7
Classifier: Programming Language :: Python :: 3.8
Classifier: Programming Language :: Python :: 3.9
Requires-Dist: numpy (>=2.0.0,<3.0.0)
